tablextract/__init__.py
tablextract/table_processing.py
tablextract/utils.py
tablextract/resources/add_render.js
tablextract-1.4.5.dist-info/LICENSE
tablextract-1.4.5.dist-info/METADATA
tablextract-1.4.5.dist-info/WHEEL
tablextract-1.4.5.dist-info/top_level.txt
tablextract-1.4.5.dist-info/RECORD
