Metadata-Version: 2.1
Name: tablextract
Version: 1.4.5
Summary: Extract the information represented in any HTML table as database-like records
Home-page: https://github.com/juancroldan/tablextract
Author: Juan C. Roldán
Author-email: juancarlos@sevilla.es
License: UNKNOWN
Platform: UNKNOWN
Classifier: Development Status :: 5 - Production/Stable
Classifier: Intended Audience :: Developers
Classifier: Natural Language :: English
Classifier: Programming Language :: Python :: 3
Classifier: Operating System :: OS Independent
Requires-Dist: requests (>=2.18.4)
Requires-Dist: bs4 (>=0.0.1)
Requires-Dist: date-extractor (>=3.9.1)
Requires-Dist: nltk (>=3.3)
Requires-Dist: scikit-learn (>=0.19.2)
Requires-Dist: selenium (>=3.14.1)
Requires-Dist: regex (>=2020.2.20)
